{
  "todos": [
    {
      "userId": 1,
      "completed": false,
      "title": "quis ut nam facilis et officia qui",
      "id": "1",
      "date": "2024-06-02",
      "subtasks": [
        {
          "id": "1721096882990",
          "title": "fd hfg tfssh gdk",
          "completed": false
        }
      ]
    },
    {
      "id": "1721096806694",
      "title": "learn js",
      "completed": false,
      "date": "2024-08-11",
      "subtasks": [
        {
          "id": "1721096835898",
          "title": "callback function",
          "completed": false
        },
        {
          "id": "1721096854320",
          "title": "promise",
          "completed": false
        }
      ]
    },
    {
      "id": "1721096821329",
      "title": "learn react",
      "completed": false,
      "date": "2024-09-07",
      "subtasks": [
        {
          "id": "1721096867731",
          "title": "hooks",
          "completed": false
        }
      ]
    },
    {
      "id": "1721097065019",
      "title": "products",
      "completed": false,
      "date": "2024-08-04",
      "subtasks": [
        {
          "id": "1721097070545",
          "title": "milk",
          "completed": false
        },
        {
          "id": "1721097077765",
          "title": "apples",
          "completed": true
        },
        {
          "id": "1721097088766",
          "title": "bread",
          "completed": false
        }
      ]
    },
    {
      "id": "1721103197339",
      "title": "HTML",
      "completed": false,
      "date": "2024-07-20",
      "subtasks": [
        {
          "id": "1721103468484",
          "title": "wlwllwlw",
          "completed": false
        }
      ]
    },
    {
      "id": "1721103773167",
      "title": "2345678765432",
      "completed": false,
      "date": "2024-07-20",
      "subtasks": [
        {
          "id": "1721103813644",
          "title": "sssss",
          "completed": false
        }
      ]
    },
    {
      "id": "1721104371867",
      "title": "skkkskskskk",
      "completed": true,
      "date": "",
      "subtasks": []
    }
  ]
}